LICENSE.txt
MANIFEST.in
setup.cfg
setup.py
contrib/foreman_dlm_updater
foreman_dlm_updater/__init__.py
foreman_dlm_updater.egg-info/PKG-INFO
foreman_dlm_updater.egg-info/SOURCES.txt
foreman_dlm_updater.egg-info/dependency_links.txt
foreman_dlm_updater.egg-info/requires.txt
foreman_dlm_updater.egg-info/top_level.txt