Metadata-Version: 1.1
Name: foreman-dlm-updater
Version: 0.0.2
Summary: ForemanDlmUpdater, Linux client counterpart to the awesome Foreman DLM plugin.
Home-page: https://github.com/schlitzered/foreman_dlm_updater
Author: schlitzer
Author-email: stephan.schultchen@gmail.com
License: MIT
Keywords: foreman,dlm
Platform: posix
Classifier: License :: OSI Approved :: MIT License
Classifier: Programming Language :: Python :: 3
